pyafiles/__init__.py
pyafiles/file.py
pyafiles-0.1.0.dist-info/METADATA
pyafiles-0.1.0.dist-info/WHEEL
pyafiles-0.1.0.dist-info/top_level.txt
pyafiles-0.1.0.dist-info/RECORD
