Metadata-Version: 2.4
Name: pyafiles
Version: 0.1.0
Summary: Minimal async file I/O wrapper using asyncio
Home-page: https://github.com/pavalso/pyafiles
Author: Pavalso
Requires-Python: >=3.7
